fuzzy_extractor/__init__.py
fuzzy_extractor-0.3.dist-info/DESCRIPTION.rst
fuzzy_extractor-0.3.dist-info/LICENSE.txt
fuzzy_extractor-0.3.dist-info/METADATA
fuzzy_extractor-0.3.dist-info/RECORD
fuzzy_extractor-0.3.dist-info/WHEEL
fuzzy_extractor-0.3.dist-info/metadata.json
fuzzy_extractor-0.3.dist-info/top_level.txt
