Metadata-Version: 2.0
Name: fuzzy-extractor
Version: 0.3
Summary: A Python implementation of fuzzy extractor
Home-page: https://github.com/carter-yagemann/python-fuzzy-extractor
Author: Carter Yagemann
Author-email: yagemann@gatech.edu
License: GPLv3+
Download-URL: https://github.com/carter-yagemann/python-fuzzy-extractor
Keywords: fuzzy extractor security
Platform: Any
Classifier: Development Status :: 5 - Production/Stable
Classifier: Intended Audience :: Developers
Classifier: License :: OSI Approved :: GNU General Public License v3 or later (GPLv3+)
Classifier: Operating System :: OS Independent
Classifier: Topic :: Software Development :: Libraries :: Python Modules
Classifier: Topic :: Security
Classifier: Topic :: Security :: Cryptography
Classifier: Topic :: Utilities
Classifier: Programming Language :: Python
Classifier: Programming Language :: Python :: 2
Classifier: Programming Language :: Python :: 2.7
Classifier: Programming Language :: Python :: 3
Classifier: Programming Language :: Python :: 3.5
Requires-Dist: fastpbkdf2
Requires-Dist: numpy
